{
  "name": "Sentry Wizard",
  "canonical": "app:sentry-wizard",
  "version": "3.16.4",
  "repo_url": "https://github.com/getsentry/sentry-wizard",
  "main_docs_url": "https://github.com/getsentry/sentry-wizard",
  "file_urls": {
    "sentry-wizard-v3.16.4.tgz": "https://github.com/getsentry/sentry-wizard/releases/tag/v3.16.4"
  },
  "files": {
    "sentry-wizard-v3.16.4.tgz": {
      "url": "https://github.com/getsentry/sentry-wizard/releases/tag/v3.16.4"
    }
  },
  "created_at": "2023-11-14T16:03:05.000Z"
}