{
  "name": "Sentry Craft",
  "canonical": "app:craft",
  "version": "1.19.0",
  "repo_url": "https://github.com/getsentry/craft",
  "main_docs_url": "https://github.com/getsentry/craft",
  "file_urls": {
    "craft": "https://downloads.sentry-cdn.com/craft/1.19.0/craft",
    "gh-pages.zip": "https://downloads.sentry-cdn.com/craft/1.19.0/gh-pages.zip",
    "sentry-craft-1.19.0.tgz": "https://downloads.sentry-cdn.com/craft/1.19.0/sentry-craft-1.19.0.tgz"
  },
  "files": {
    "gh-pages.zip": {
      "url": "https://downloads.sentry-cdn.com/craft/1.19.0/gh-pages.zip",
      "checksums": {
        "sha256-hex": "3acf9d60b7a5593973daec31ed0e6eda618920a5eddc627ef495d3b7e2292132"
      }
    },
    "sentry-craft-1.19.0.tgz": {
      "url": "https://downloads.sentry-cdn.com/craft/1.19.0/sentry-craft-1.19.0.tgz",
      "checksums": {
        "sha256-hex": "4ee57bb3c5aac8f0703d50917600a221b1ad13658ed291f53e4b76151073983d"
      }
    },
    "craft": {
      "url": "https://downloads.sentry-cdn.com/craft/1.19.0/craft",
      "checksums": {
        "sha256-hex": "2d09074389bd89c8f87d2b59d0bb6b1362f4d82628fefe3caea2e0b99aabf9a7"
      }
    }
  },
  "created_at": "2024-04-15T14:31:22.500Z"
}
