{
  "name": "Sentry CLI",
  "canonical": "app:sentry-cli",
  "version": "1.38.0",
  "repo_url": "https://github.com/getsentry/sentry-cli",
  "main_docs_url": "https://docs.sentry.io/learn/cli",
  "file_urls": {
    "sentry-cli-Darwin-x86_64": "https://downloads.sentry-cdn.com/sentry-cli/1.38.0/sentry-cli-Darwin-x86_64",
    "sentry-cli-Linux-i686": "https://downloads.sentry-cdn.com/sentry-cli/1.38.0/sentry-cli-Linux-i686",
    "sentry-cli-Linux-x86_64": "https://downloads.sentry-cdn.com/sentry-cli/1.38.0/sentry-cli-Linux-x86_64",
    "sentry-cli-Windows-i686.exe": "https://downloads.sentry-cdn.com/sentry-cli/1.38.0/sentry-cli-Windows-i686.exe",
    "sentry-cli-Windows-x86_64.exe": "https://downloads.sentry-cdn.com/sentry-cli/1.38.0/sentry-cli-Windows-x86_64.exe"
  }
}
