{
  "name": "Sentry CLI",
  "canonical": "app:sentry-cli",
  "version": "1.56.0",
  "repo_url": "https://github.com/getsentry/sentry-cli",
  "main_docs_url": "https://docs.sentry.io/learn/cli",
  "file_urls": {
    "sentry-cli-Darwin-x86_64": "https://downloads.sentry-cdn.com/sentry-cli/1.56.0/sentry-cli-Darwin-x86_64",
    "sentry-cli-Linux-i686": "https://downloads.sentry-cdn.com/sentry-cli/1.56.0/sentry-cli-Linux-i686",
    "sentry-cli-Linux-x86_64": "https://downloads.sentry-cdn.com/sentry-cli/1.56.0/sentry-cli-Linux-x86_64",
    "sentry-cli-Windows-i686.exe": "https://downloads.sentry-cdn.com/sentry-cli/1.56.0/sentry-cli-Windows-i686.exe",
    "sentry-cli-Windows-x86_64.exe": "https://downloads.sentry-cdn.com/sentry-cli/1.56.0/sentry-cli-Windows-x86_64.exe"
  },
  "files": {
    "sentry-cli-Darwin-x86_64": {
      "url": "https://downloads.sentry-cdn.com/sentry-cli/1.56.0/sentry-cli-Darwin-x86_64",
      "checksums": {
        "sha256-hex": "c7d10b8bb8dae56792e46e312811455bf950d6bb6798df5c31bdbec743166e47"
      }
    },
    "sentry-cli-Linux-i686": {
      "url": "https://downloads.sentry-cdn.com/sentry-cli/1.56.0/sentry-cli-Linux-i686",
      "checksums": {
        "sha256-hex": "4b69395175aafa628ad695ad998a82a73383512f722fa25d5b6ef5c341915565"
      }
    },
    "sentry-cli-Linux-x86_64": {
      "url": "https://downloads.sentry-cdn.com/sentry-cli/1.56.0/sentry-cli-Linux-x86_64",
      "checksums": {
        "sha256-hex": "f525b632306d004213791a114752f88fe2b08a8174a6887beacac49a77d851d1"
      }
    },
    "sentry-cli-Windows-i686.exe": {
      "url": "https://downloads.sentry-cdn.com/sentry-cli/1.56.0/sentry-cli-Windows-i686.exe",
      "checksums": {
        "sha256-hex": "912c87c65e8fe68018b6be61c4849996d401bd63b9a4b390e7b5edaa46394c4e"
      }
    },
    "sentry-cli-Windows-x86_64.exe": {
      "url": "https://downloads.sentry-cdn.com/sentry-cli/1.56.0/sentry-cli-Windows-x86_64.exe",
      "checksums": {
        "sha256-hex": "fb6322d74c546bf02977614c5292ac5ebce2a9163f1fc27d0b29c12a46851677"
      }
    }
  },
  "created_at": "2020-09-02T11:57:20.000Z"
}
