{
  "name": "Sentry CLI",
  "canonical": "app:sentry-cli",
  "version": "1.74.5",
  "repo_url": "https://github.com/getsentry/sentry-cli",
  "main_docs_url": "https://docs.sentry.io/learn/cli",
  "file_urls": {
    "sentry-cli-1.74.5.tgz": "https://downloads.sentry-cdn.com/sentry-cli/1.74.5/sentry-cli-1.74.5.tgz",
    "sentry-cli-Darwin-arm64": "https://downloads.sentry-cdn.com/sentry-cli/1.74.5/sentry-cli-Darwin-arm64",
    "sentry-cli-Darwin-universal": "https://downloads.sentry-cdn.com/sentry-cli/1.74.5/sentry-cli-Darwin-universal",
    "sentry-cli-Darwin-x86_64": "https://downloads.sentry-cdn.com/sentry-cli/1.74.5/sentry-cli-Darwin-x86_64",
    "sentry-cli-Linux-aarch64": "https://downloads.sentry-cdn.com/sentry-cli/1.74.5/sentry-cli-Linux-aarch64",
    "sentry-cli-Linux-armv7": "https://downloads.sentry-cdn.com/sentry-cli/1.74.5/sentry-cli-Linux-armv7",
    "sentry-cli-Linux-i686": "https://downloads.sentry-cdn.com/sentry-cli/1.74.5/sentry-cli-Linux-i686",
    "sentry-cli-Linux-x86_64": "https://downloads.sentry-cdn.com/sentry-cli/1.74.5/sentry-cli-Linux-x86_64",
    "sentry-cli-Windows-i686.exe": "https://downloads.sentry-cdn.com/sentry-cli/1.74.5/sentry-cli-Windows-i686.exe",
    "sentry-cli-Windows-x86_64.exe": "https://downloads.sentry-cdn.com/sentry-cli/1.74.5/sentry-cli-Windows-x86_64.exe"
  },
  "files": {
    "sentry-cli-1.74.5.tgz": {
      "url": "https://downloads.sentry-cdn.com/sentry-cli/1.74.5/sentry-cli-1.74.5.tgz",
      "checksums": {
        "sha256-hex": "56c2af3d4f82a5d890b17787342075587fcdd04eb4b55f6a02cfe4329c4d24ba"
      }
    },
    "sentry-cli-Darwin-arm64": {
      "url": "https://downloads.sentry-cdn.com/sentry-cli/1.74.5/sentry-cli-Darwin-arm64",
      "checksums": {
        "sha256-hex": "850e9b5635462e373d73d7a6f60601da4cf2891b1a6405eebc173dae92841f08"
      }
    },
    "sentry-cli-Darwin-x86_64": {
      "url": "https://downloads.sentry-cdn.com/sentry-cli/1.74.5/sentry-cli-Darwin-x86_64",
      "checksums": {
        "sha256-hex": "9012e0ec228dab954e330409bfb2b70f10a4a18d96a3ac858e490db2e5b94035"
      }
    },
    "sentry-cli-Linux-armv7": {
      "url": "https://downloads.sentry-cdn.com/sentry-cli/1.74.5/sentry-cli-Linux-armv7",
      "checksums": {
        "sha256-hex": "4c2689cc0d27b78e1a72f7370c14cc791cbbae4a1ce0803dc23f8106f3bbf16a"
      }
    },
    "sentry-cli-Linux-aarch64": {
      "url": "https://downloads.sentry-cdn.com/sentry-cli/1.74.5/sentry-cli-Linux-aarch64",
      "checksums": {
        "sha256-hex": "93e8e9ddd46c210900567614622f1b71383aad81814860dff054b38da66e8ed0"
      }
    },
    "sentry-cli-Darwin-universal": {
      "url": "https://downloads.sentry-cdn.com/sentry-cli/1.74.5/sentry-cli-Darwin-universal",
      "checksums": {
        "sha256-hex": "85d662e19e59a564708bd09a17857b6d7a13d45fde5f7f761365568185679cdd"
      }
    },
    "sentry-cli-Windows-i686.exe": {
      "url": "https://downloads.sentry-cdn.com/sentry-cli/1.74.5/sentry-cli-Windows-i686.exe",
      "checksums": {
        "sha256-hex": "4b5ab85d99fe29f0b5937f9344944ec77663adc928c85d5887f32cfc655a6116"
      }
    },
    "sentry-cli-Windows-x86_64.exe": {
      "url": "https://downloads.sentry-cdn.com/sentry-cli/1.74.5/sentry-cli-Windows-x86_64.exe",
      "checksums": {
        "sha256-hex": "1767f6bdc4a8a5d9542cc000a3cd4041a86809d911a2e172cb77d04a2eee4e3c"
      }
    },
    "sentry-cli-Linux-i686": {
      "url": "https://downloads.sentry-cdn.com/sentry-cli/1.74.5/sentry-cli-Linux-i686",
      "checksums": {
        "sha256-hex": "e90923c771968751a82efa17bb0a1b2a2747f8f53b95af016ca99c84b88dc263"
      }
    },
    "sentry-cli-Linux-x86_64": {
      "url": "https://downloads.sentry-cdn.com/sentry-cli/1.74.5/sentry-cli-Linux-x86_64",
      "checksums": {
        "sha256-hex": "b22afdbac4258b19896e2f77230b119b14b71944cdd86b4b4904f1d6641af5cd"
      }
    }
  },
  "createdAt": "2022-07-20T10:44:21.000Z"
}
