{
  "name": "Sentry CLI",
  "canonical": "app:sentry-cli",
  "version": "2.32.2",
  "repo_url": "https://github.com/getsentry/sentry-cli",
  "main_docs_url": "https://docs.sentry.io/learn/cli",
  "file_urls": {
    "sentry-cli-darwin-2.32.2.tgz": "https://downloads.sentry-cdn.com/sentry-cli/2.32.2/sentry-cli-darwin-2.32.2.tgz",
    "sentry-cli-linux-arm-2.32.2.tgz": "https://downloads.sentry-cdn.com/sentry-cli/2.32.2/sentry-cli-linux-arm-2.32.2.tgz",
    "sentry-cli-linux-arm64-2.32.2.tgz": "https://downloads.sentry-cdn.com/sentry-cli/2.32.2/sentry-cli-linux-arm64-2.32.2.tgz",
    "sentry-cli-linux-i686-2.32.2.tgz": "https://downloads.sentry-cdn.com/sentry-cli/2.32.2/sentry-cli-linux-i686-2.32.2.tgz",
    "sentry-cli-linux-x64-2.32.2.tgz": "https://downloads.sentry-cdn.com/sentry-cli/2.32.2/sentry-cli-linux-x64-2.32.2.tgz",
    "sentry-cli-2.32.2.tgz": "https://downloads.sentry-cdn.com/sentry-cli/2.32.2/sentry-cli-2.32.2.tgz",
    "sentry-cli-Darwin-arm64": "https://downloads.sentry-cdn.com/sentry-cli/2.32.2/sentry-cli-Darwin-arm64",
    "sentry-cli-Darwin-universal": "https://downloads.sentry-cdn.com/sentry-cli/2.32.2/sentry-cli-Darwin-universal",
    "sentry-cli-Darwin-x86_64": "https://downloads.sentry-cdn.com/sentry-cli/2.32.2/sentry-cli-Darwin-x86_64",
    "sentry-cli-Linux-aarch64": "https://downloads.sentry-cdn.com/sentry-cli/2.32.2/sentry-cli-Linux-aarch64",
    "sentry-cli-Linux-armv7": "https://downloads.sentry-cdn.com/sentry-cli/2.32.2/sentry-cli-Linux-armv7",
    "sentry-cli-Linux-i686": "https://downloads.sentry-cdn.com/sentry-cli/2.32.2/sentry-cli-Linux-i686",
    "sentry-cli-Linux-x86_64": "https://downloads.sentry-cdn.com/sentry-cli/2.32.2/sentry-cli-Linux-x86_64",
    "sentry-cli-Windows-i686.exe": "https://downloads.sentry-cdn.com/sentry-cli/2.32.2/sentry-cli-Windows-i686.exe",
    "sentry-cli-Windows-x86_64.exe": "https://downloads.sentry-cdn.com/sentry-cli/2.32.2/sentry-cli-Windows-x86_64.exe",
    "sentry_cli-2.32.2-py3-none-macosx_10_15_x86_64.whl": "https://downloads.sentry-cdn.com/sentry-cli/2.32.2/sentry_cli-2.32.2-py3-none-macosx_10_15_x86_64.whl",
    "sentry_cli-2.32.2-py3-none-macosx_11_0_arm64.whl": "https://downloads.sentry-cdn.com/sentry-cli/2.32.2/sentry_cli-2.32.2-py3-none-macosx_11_0_arm64.whl",
    "sentry_cli-2.32.2-py3-none-macosx_11_0_universal2.whl": "https://downloads.sentry-cdn.com/sentry-cli/2.32.2/sentry_cli-2.32.2-py3-none-macosx_11_0_universal2.whl",
    "sentry_cli-2.32.2-py3-none-manylinux_2_17_aarch64.manylinux2014_aarch64.musllinux_1_2_aarch64.whl": "https://downloads.sentry-cdn.com/sentry-cli/2.32.2/sentry_cli-2.32.2-py3-none-manylinux_2_17_aarch64.manylinux2014_aarch64.musllinux_1_2_aarch64.whl",
    "sentry_cli-2.32.2-py3-none-manylinux_2_17_armv7l.manylinux2014_armv7l.musllinux_1_2_armv7l.whl": "https://downloads.sentry-cdn.com/sentry-cli/2.32.2/sentry_cli-2.32.2-py3-none-manylinux_2_17_armv7l.manylinux2014_armv7l.musllinux_1_2_armv7l.whl",
    "sentry_cli-2.32.2-py3-none-manylinux_2_17_i686.manylinux2014_i686.musllinux_1_2_i686.whl": "https://downloads.sentry-cdn.com/sentry-cli/2.32.2/sentry_cli-2.32.2-py3-none-manylinux_2_17_i686.manylinux2014_i686.musllinux_1_2_i686.whl",
    "sentry_cli-2.32.2-py3-none-manylinux_2_17_x86_64.manylinux2014_x86_64.musllinux_1_2_x86_64.whl": "https://downloads.sentry-cdn.com/sentry-cli/2.32.2/sentry_cli-2.32.2-py3-none-manylinux_2_17_x86_64.manylinux2014_x86_64.musllinux_1_2_x86_64.whl",
    "sentry_cli-2.32.2-py3-none-win32.whl": "https://downloads.sentry-cdn.com/sentry-cli/2.32.2/sentry_cli-2.32.2-py3-none-win32.whl",
    "sentry_cli-2.32.2-py3-none-win_amd64.whl": "https://downloads.sentry-cdn.com/sentry-cli/2.32.2/sentry_cli-2.32.2-py3-none-win_amd64.whl",
    "sentry_cli-2.32.2.tar.gz": "https://downloads.sentry-cdn.com/sentry-cli/2.32.2/sentry_cli-2.32.2.tar.gz",
    "sentry-cli-win32-i686-2.32.2.tgz": "https://downloads.sentry-cdn.com/sentry-cli/2.32.2/sentry-cli-win32-i686-2.32.2.tgz",
    "sentry-cli-win32-x64-2.32.2.tgz": "https://downloads.sentry-cdn.com/sentry-cli/2.32.2/sentry-cli-win32-x64-2.32.2.tgz"
  },
  "created_at": "2024-07-15T14:54:05.565Z",
  "files": {
    "sentry-cli-darwin-2.32.2.tgz": {
      "url": "https://downloads.sentry-cdn.com/sentry-cli/2.32.2/sentry-cli-darwin-2.32.2.tgz",
      "checksums": {
        "sha256-hex": "b9cff08322fbf6627b8e124d5acfd62c322448c393334fdf68753e64603eb58f"
      }
    },
    "sentry-cli-linux-arm-2.32.2.tgz": {
      "url": "https://downloads.sentry-cdn.com/sentry-cli/2.32.2/sentry-cli-linux-arm-2.32.2.tgz",
      "checksums": {
        "sha256-hex": "baee581e54c8473daedd7d4207e5b37971fac1b6db612f1b8b0de00531e48a87"
      }
    },
    "sentry-cli-linux-arm64-2.32.2.tgz": {
      "url": "https://downloads.sentry-cdn.com/sentry-cli/2.32.2/sentry-cli-linux-arm64-2.32.2.tgz",
      "checksums": {
        "sha256-hex": "9b01e2998ee47adc74a323619ab64157fe04eecbec6637e2ee3c73ea37c1d00e"
      }
    },
    "sentry-cli-linux-i686-2.32.2.tgz": {
      "url": "https://downloads.sentry-cdn.com/sentry-cli/2.32.2/sentry-cli-linux-i686-2.32.2.tgz",
      "checksums": {
        "sha256-hex": "f1ef968650dc7a47fd9657715a0d231f03a3ceb565846b87439629f9c8b16597"
      }
    },
    "sentry-cli-linux-x64-2.32.2.tgz": {
      "url": "https://downloads.sentry-cdn.com/sentry-cli/2.32.2/sentry-cli-linux-x64-2.32.2.tgz",
      "checksums": {
        "sha256-hex": "68adb8f66f876847233018ee1609c4843afb9accbc76313cfd5bc0586da01c58"
      }
    },
    "sentry-cli-2.32.2.tgz": {
      "url": "https://downloads.sentry-cdn.com/sentry-cli/2.32.2/sentry-cli-2.32.2.tgz",
      "checksums": {
        "sha256-hex": "dbf06e7cd9c2c6c5edc8b9122bf45ea3d8c6c437e59ea2c8087743c81e980c22"
      }
    },
    "sentry-cli-Darwin-arm64": {
      "url": "https://downloads.sentry-cdn.com/sentry-cli/2.32.2/sentry-cli-Darwin-arm64",
      "checksums": {
        "sha256-hex": "96e0a0583ae0166f2c57a9d6e73f81affdbbf76c4bf4c659ba79c74f49cf1d56"
      }
    },
    "sentry-cli-Darwin-universal": {
      "url": "https://downloads.sentry-cdn.com/sentry-cli/2.32.2/sentry-cli-Darwin-universal",
      "checksums": {
        "sha256-hex": "e420908b480fe4e7d280df86392b1c3785e252bed14b53c18df3e4701d1b82e3"
      }
    },
    "sentry-cli-Darwin-x86_64": {
      "url": "https://downloads.sentry-cdn.com/sentry-cli/2.32.2/sentry-cli-Darwin-x86_64",
      "checksums": {
        "sha256-hex": "08b840b088e6ad13bd1d2d5671ed53b3ee319f49a8fd80678971587431af1c95"
      }
    },
    "sentry-cli-Linux-aarch64": {
      "url": "https://downloads.sentry-cdn.com/sentry-cli/2.32.2/sentry-cli-Linux-aarch64",
      "checksums": {
        "sha256-hex": "b74cb1b7ea58ffc984c873442f2dd9610c680cfce6e333ad6f37cb6ae0ae4275"
      }
    },
    "sentry-cli-Linux-armv7": {
      "url": "https://downloads.sentry-cdn.com/sentry-cli/2.32.2/sentry-cli-Linux-armv7",
      "checksums": {
        "sha256-hex": "2bfc107dd0b3671771674b50a4332e7f1912a7fd991c59b1cfe34b6043ac0658"
      }
    },
    "sentry-cli-Linux-i686": {
      "url": "https://downloads.sentry-cdn.com/sentry-cli/2.32.2/sentry-cli-Linux-i686",
      "checksums": {
        "sha256-hex": "663d73e161062905ccfa8caff7287592d0b709f6e4c26b2b2083e6d46adc4a41"
      }
    },
    "sentry-cli-Linux-x86_64": {
      "url": "https://downloads.sentry-cdn.com/sentry-cli/2.32.2/sentry-cli-Linux-x86_64",
      "checksums": {
        "sha256-hex": "c69097afb8de93417805b521490adca1a5f35f3453da837273c1738392628710"
      }
    },
    "sentry-cli-Windows-i686.exe": {
      "url": "https://downloads.sentry-cdn.com/sentry-cli/2.32.2/sentry-cli-Windows-i686.exe",
      "checksums": {
        "sha256-hex": "9605fb4702af3d76a4ce492db9cf229e29bbc59906f258509f2d6464504919d5"
      }
    },
    "sentry-cli-Windows-x86_64.exe": {
      "url": "https://downloads.sentry-cdn.com/sentry-cli/2.32.2/sentry-cli-Windows-x86_64.exe",
      "checksums": {
        "sha256-hex": "3ec74a179b5ef172f24f8ba8ab0d6a6ce2ccfe44e9575d2fe4e63e42a4b63aae"
      }
    },
    "sentry_cli-2.32.2-py3-none-macosx_10_15_x86_64.whl": {
      "url": "https://downloads.sentry-cdn.com/sentry-cli/2.32.2/sentry_cli-2.32.2-py3-none-macosx_10_15_x86_64.whl",
      "checksums": {
        "sha256-hex": "718cac8e6512742d8a82fe0e54976686a147f89a1234be81bbfadde691738053"
      }
    },
    "sentry_cli-2.32.2-py3-none-macosx_11_0_arm64.whl": {
      "url": "https://downloads.sentry-cdn.com/sentry-cli/2.32.2/sentry_cli-2.32.2-py3-none-macosx_11_0_arm64.whl",
      "checksums": {
        "sha256-hex": "834062564566a41b350d173bc0af8575db360362a138fc3f5ff32f2a58039374"
      }
    },
    "sentry_cli-2.32.2-py3-none-macosx_11_0_universal2.whl": {
      "url": "https://downloads.sentry-cdn.com/sentry-cli/2.32.2/sentry_cli-2.32.2-py3-none-macosx_11_0_universal2.whl",
      "checksums": {
        "sha256-hex": "d8b300420e8353af1667b5e617a0a2076709ba5e17a8be2529f082c23d0fa5b9"
      }
    },
    "sentry_cli-2.32.2-py3-none-manylinux_2_17_aarch64.manylinux2014_aarch64.musllinux_1_2_aarch64.whl": {
      "url": "https://downloads.sentry-cdn.com/sentry-cli/2.32.2/sentry_cli-2.32.2-py3-none-manylinux_2_17_aarch64.manylinux2014_aarch64.musllinux_1_2_aarch64.whl",
      "checksums": {
        "sha256-hex": "fb09585560f4835fe0ff8d6be6839291c548229ce09b48501380a868d6d7500b"
      }
    },
    "sentry_cli-2.32.2-py3-none-manylinux_2_17_armv7l.manylinux2014_armv7l.musllinux_1_2_armv7l.whl": {
      "url": "https://downloads.sentry-cdn.com/sentry-cli/2.32.2/sentry_cli-2.32.2-py3-none-manylinux_2_17_armv7l.manylinux2014_armv7l.musllinux_1_2_armv7l.whl",
      "checksums": {
        "sha256-hex": "5decfcb47c199e4123b3b836a69410c10f69e13e263c0049416f08ef438108f4"
      }
    },
    "sentry_cli-2.32.2-py3-none-manylinux_2_17_i686.manylinux2014_i686.musllinux_1_2_i686.whl": {
      "url": "https://downloads.sentry-cdn.com/sentry-cli/2.32.2/sentry_cli-2.32.2-py3-none-manylinux_2_17_i686.manylinux2014_i686.musllinux_1_2_i686.whl",
      "checksums": {
        "sha256-hex": "fa5ac29a3a3c9ee495255955c38547ddedefa70457f506358493f83f5d45c2e2"
      }
    },
    "sentry_cli-2.32.2-py3-none-manylinux_2_17_x86_64.manylinux2014_x86_64.musllinux_1_2_x86_64.whl": {
      "url": "https://downloads.sentry-cdn.com/sentry-cli/2.32.2/sentry_cli-2.32.2-py3-none-manylinux_2_17_x86_64.manylinux2014_x86_64.musllinux_1_2_x86_64.whl",
      "checksums": {
        "sha256-hex": "0d1c70bf0cc76a43239e134ae8aa7879f757120280586e72d4a434bbe3b5b119"
      }
    },
    "sentry_cli-2.32.2-py3-none-win32.whl": {
      "url": "https://downloads.sentry-cdn.com/sentry-cli/2.32.2/sentry_cli-2.32.2-py3-none-win32.whl",
      "checksums": {
        "sha256-hex": "c712476308f62373f493d4d7098139a67317e83027f33b322d5f43ad35c1a85b"
      }
    },
    "sentry_cli-2.32.2-py3-none-win_amd64.whl": {
      "url": "https://downloads.sentry-cdn.com/sentry-cli/2.32.2/sentry_cli-2.32.2-py3-none-win_amd64.whl",
      "checksums": {
        "sha256-hex": "a7914ce26c49a2c992756a764a7d28909a9d9f86404a264478909f41cc1579ce"
      }
    },
    "sentry_cli-2.32.2.tar.gz": {
      "url": "https://downloads.sentry-cdn.com/sentry-cli/2.32.2/sentry_cli-2.32.2.tar.gz",
      "checksums": {
        "sha256-hex": "e8513553029b427ecde98e8106d5dff58c4e255a338f4efe01dcf8275ce0e939"
      }
    },
    "sentry-cli-win32-i686-2.32.2.tgz": {
      "url": "https://downloads.sentry-cdn.com/sentry-cli/2.32.2/sentry-cli-win32-i686-2.32.2.tgz",
      "checksums": {
        "sha256-hex": "27c85f4cb6ec21bc1c56c805c3ffba3996aa096e6ef9566fd9fe7376fa1bf9df"
      }
    },
    "sentry-cli-win32-x64-2.32.2.tgz": {
      "url": "https://downloads.sentry-cdn.com/sentry-cli/2.32.2/sentry-cli-win32-x64-2.32.2.tgz",
      "checksums": {
        "sha256-hex": "6ef526431d36a1835b7c4a7ee8ce0d1ba4b0d9c28811be542f7a90b3db7eeb8f"
      }
    }
  }
}
