{
  "name": "Sentry CLI",
  "canonical": "app:sentry-cli",
  "version": "2.8.0",
  "repo_url": "https://github.com/getsentry/sentry-cli",
  "main_docs_url": "https://docs.sentry.io/learn/cli",
  "file_urls": {
    "sentry-cli-2.8.0.tgz": "https://downloads.sentry-cdn.com/sentry-cli/2.8.0/sentry-cli-2.8.0.tgz",
    "sentry-cli-Darwin-arm64": "https://downloads.sentry-cdn.com/sentry-cli/2.8.0/sentry-cli-Darwin-arm64",
    "sentry-cli-Darwin-universal": "https://downloads.sentry-cdn.com/sentry-cli/2.8.0/sentry-cli-Darwin-universal",
    "sentry-cli-Darwin-x86_64": "https://downloads.sentry-cdn.com/sentry-cli/2.8.0/sentry-cli-Darwin-x86_64",
    "sentry-cli-Linux-aarch64": "https://downloads.sentry-cdn.com/sentry-cli/2.8.0/sentry-cli-Linux-aarch64",
    "sentry-cli-Linux-armv7": "https://downloads.sentry-cdn.com/sentry-cli/2.8.0/sentry-cli-Linux-armv7",
    "sentry-cli-Linux-i686": "https://downloads.sentry-cdn.com/sentry-cli/2.8.0/sentry-cli-Linux-i686",
    "sentry-cli-Linux-x86_64": "https://downloads.sentry-cdn.com/sentry-cli/2.8.0/sentry-cli-Linux-x86_64",
    "sentry-cli-Windows-i686.exe": "https://downloads.sentry-cdn.com/sentry-cli/2.8.0/sentry-cli-Windows-i686.exe",
    "sentry-cli-Windows-x86_64.exe": "https://downloads.sentry-cdn.com/sentry-cli/2.8.0/sentry-cli-Windows-x86_64.exe"
  },
  "files": {
    "sentry-cli-2.8.0.tgz": {
      "url": "https://downloads.sentry-cdn.com/sentry-cli/2.8.0/sentry-cli-2.8.0.tgz",
      "checksums": {
        "sha256-hex": "ca1e0f05fb057acb1e221dcfbb1ad535277477f9509dee1f344562134356d36f"
      }
    },
    "sentry-cli-Darwin-arm64": {
      "url": "https://downloads.sentry-cdn.com/sentry-cli/2.8.0/sentry-cli-Darwin-arm64",
      "checksums": {
        "sha256-hex": "772a45b9e9935f1105bdd3bd63f448bd78432fc4616c253cc6aa295f743c364c"
      }
    },
    "sentry-cli-Darwin-universal": {
      "url": "https://downloads.sentry-cdn.com/sentry-cli/2.8.0/sentry-cli-Darwin-universal",
      "checksums": {
        "sha256-hex": "a2aadaf804fad99ac70f52a32bf1f0ff53327ed52c2a723fea04bbe9cbde3485"
      }
    },
    "sentry-cli-Darwin-x86_64": {
      "url": "https://downloads.sentry-cdn.com/sentry-cli/2.8.0/sentry-cli-Darwin-x86_64",
      "checksums": {
        "sha256-hex": "eb4f04ad6c577fcf397a46c58e9d9a7073d777237f70a25af5c30c3f00060e55"
      }
    },
    "sentry-cli-Linux-aarch64": {
      "url": "https://downloads.sentry-cdn.com/sentry-cli/2.8.0/sentry-cli-Linux-aarch64",
      "checksums": {
        "sha256-hex": "652b0a6fb992fac95b80bcc6d2f59868750ac22eb2ff4156d3c8bd646c934c3b"
      }
    },
    "sentry-cli-Linux-armv7": {
      "url": "https://downloads.sentry-cdn.com/sentry-cli/2.8.0/sentry-cli-Linux-armv7",
      "checksums": {
        "sha256-hex": "0c41f307f3f2a69270150b1b8fd41acbbcfbe8730610d3a7dd8bdd7aecac6613"
      }
    },
    "sentry-cli-Linux-i686": {
      "url": "https://downloads.sentry-cdn.com/sentry-cli/2.8.0/sentry-cli-Linux-i686",
      "checksums": {
        "sha256-hex": "b543cf7394a0516fa85d69a63a8f0a91a5aa3ccceb5d40355193f8491224b1bf"
      }
    },
    "sentry-cli-Linux-x86_64": {
      "url": "https://downloads.sentry-cdn.com/sentry-cli/2.8.0/sentry-cli-Linux-x86_64",
      "checksums": {
        "sha256-hex": "bbbd739afc0d8a6736ae45e5f6fcd6db87f7abf45de9fa76e5621834f2dfd15d"
      }
    },
    "sentry-cli-Windows-i686.exe": {
      "url": "https://downloads.sentry-cdn.com/sentry-cli/2.8.0/sentry-cli-Windows-i686.exe",
      "checksums": {
        "sha256-hex": "760d313eddd0f1dd5b23301635dc7c4512b021d9dc01067eb7fa6b54e4789078"
      }
    },
    "sentry-cli-Windows-x86_64.exe": {
      "url": "https://downloads.sentry-cdn.com/sentry-cli/2.8.0/sentry-cli-Windows-x86_64.exe",
      "checksums": {
        "sha256-hex": "a89a4ca913be1e5ff9ccb456b5bde221bb59128eb5ca2de0f6bcd09a119471ee"
      }
    }
  },
  "createdAt": "2022-10-24T11:32:48.000Z"
}
